tinytapeout/cores/sim_spi_flash/spiflash_orig.v
/*
 *  PicoSoC - A simple example SoC using PicoRV32
 *
 *  Copyright (C) 2017  Clifford Wolf <clifford@clifford.at>
 *
 *  Permission to use, copy, modify, and/or distribute this software for any
 *  purpose with or without fee is hereby granted, provided that the above
 *  copyright notice and this permission notice appear in all copies.
 *
 *  THE SOFTWARE IS PROVIDED "AS IS" AND THE AUTHOR DISCLAIMS ALL WARRANTIES
 *  WITH REGARD TO THIS SOFTWARE INCLUDING ALL IMPLIED WARRANTIES OF
 *  MERCHANTABILITY AND FITNESS. IN NO EVENT SHALL THE AUTHOR BE LIABLE FOR
 *  ANY SPECIAL, DIRECT, INDIRECT, OR CONSEQUENTIAL DAMAGES OR ANY DAMAGES
 *  WHATSOEVER RESULTING FROM LOSS OF USE, DATA OR PROFITS, WHETHER IN AN
 *  ACTION OF CONTRACT, NEGLIGENCE OR OTHER TORTIOUS ACTION, ARISING OUT OF
 *  OR IN CONNECTION WITH THE USE OR PERFORMANCE OF THIS SOFTWARE.
 *
 */

`timescale 1 ns / 1 ps

//
// Simple SPI flash simulation model
//
// This model samples io input signals 1ns before the SPI clock edge and
// updates output signals 1ns after the SPI clock edge.
//
// Supported commands:
//    AB, B9, FF, 03, BB, EB, ED
//
// Well written SPI flash data sheets:
//    Cypress S25FL064L http://www.cypress.com/file/316661/download
//    Cypress S25FL128L http://www.cypress.com/file/316171/download
//

module spiflash (
	input csb,
	input clk,
	inout io0, // MOSI
	inout io1, // MISO
	inout io2,
	inout io3
);
	localparam verbose = 0;
	localparam integer latency = 8;
	
	reg [7:0] buffer;
	integer bitcount = 0;
	integer bytecount = 0;
	integer dummycount = 0;

	reg [7:0] spi_cmd;
	reg [7:0] xip_cmd = 0;
	reg [23:0] spi_addr;

	reg [7:0] spi_in;
	reg [7:0] spi_out;
	reg spi_io_vld;

	reg powered_up = 1;

	localparam [3:0] mode_spi         = 1;
	localparam [3:0] mode_dspi_rd     = 2;
	localparam [3:0] mode_dspi_wr     = 3;
	localparam [3:0] mode_qspi_rd     = 4;
	localparam [3:0] mode_qspi_wr     = 5;
	localparam [3:0] mode_qspi_ddr_rd = 6;
	localparam [3:0] mode_qspi_ddr_wr = 7;

	reg [3:0] mode = 0;
	reg [3:0] next_mode = 0;

	reg io0_oe = 0;
	reg io1_oe = 0;
	reg io2_oe = 0;
	reg io3_oe = 0;

	reg io0_dout = 0;
	reg io1_dout = 0;
	reg io2_dout = 0;
	reg io3_dout = 0;

	assign #1 io0 = io0_oe ? io0_dout : 1'bz;
	assign #1 io1 = io1_oe ? io1_dout : 1'bz;
	assign #1 io2 = io2_oe ? io2_dout : 1'bz;
	assign #1 io3 = io3_oe ? io3_dout : 1'bz;

	wire io0_delayed;
	wire io1_delayed;
	wire io2_delayed;
	wire io3_delayed;

	assign #1 io0_delayed = io0;
	assign #1 io1_delayed = io1;
	assign #1 io2_delayed = io2;
	assign #1 io3_delayed = io3;

	// 16 MB (128Mb) Flash
	reg [7:0] memory [0:4*1024-1];

	reg [1023:0] firmware_file;
	initial begin
		if (!$value$plusargs("firmware=%s", firmware_file))
			firmware_file = "firmware_flash.hex";
		$readmemh(firmware_file, memory);
	end

	task spi_action;
		begin
			spi_in = buffer;

			if (bytecount == 1) begin
				spi_cmd = buffer;

				if (spi_cmd == 8'h ab)
					powered_up = 1;

				if (spi_cmd == 8'h b9)
					powered_up = 0;

				if (spi_cmd == 8'h ff)
					xip_cmd = 0;
			end

			if (powered_up && spi_cmd == 'h 03) begin
				if (bytecount == 2)
					spi_addr[23:16] = buffer;

				if (bytecount == 3)
					spi_addr[15:8] = buffer;

				if (bytecount == 4)
					spi_addr[7:0] = buffer;

				if (bytecount >= 4) begin
					buffer = memory[spi_addr];
					spi_addr = spi_addr + 1;
				end
			end

			if (powered_up && spi_cmd == 'h bb) begin
				if (bytecount == 1)
					mode = mode_dspi_rd;

				if (bytecount == 2)
					spi_addr[23:16] = buffer;

				if (bytecount == 3)
					spi_addr[15:8] = buffer;

				if (bytecount == 4)
					spi_addr[7:0] = buffer;

				if (bytecount == 5) begin
					xip_cmd = (buffer == 8'h a5) ? spi_cmd : 8'h 00;
					mode = mode_dspi_wr;
					dummycount = latency;
				end

				if (bytecount >= 5) begin
					buffer = memory[spi_addr];
					spi_addr = spi_addr + 1;
				end
			end

			if (powered_up && spi_cmd == 'h eb) begin
				if (bytecount == 1)
					mode = mode_qspi_rd;

				if (bytecount == 2)
					spi_addr[23:16] = buffer;

				if (bytecount == 3)
					spi_addr[15:8] = buffer;

				if (bytecount == 4)
					spi_addr[7:0] = buffer;

				if (bytecount == 5) begin
					xip_cmd = (buffer == 8'h a5) ? spi_cmd : 8'h 00;
					mode = mode_qspi_wr;
					dummycount = latency;
				end

				if (bytecount >= 5) begin
					buffer = memory[spi_addr];
					spi_addr = spi_addr + 1;
				end
			end

			if (powered_up && spi_cmd == 'h ed) begin
				if (bytecount == 1)
					next_mode = mode_qspi_ddr_rd;

				if (bytecount == 2)
					spi_addr[23:16] = buffer;

				if (bytecount == 3)
					spi_addr[15:8] = buffer;

				if (bytecount == 4)
					spi_addr[7:0] = buffer;

				if (bytecount == 5) begin
					xip_cmd = (buffer == 8'h a5) ? spi_cmd : 8'h 00;
					mode = mode_qspi_ddr_wr;
					dummycount = latency;
				end

				if (bytecount >= 5) begin
					buffer = memory[spi_addr];
					spi_addr = spi_addr + 1;
				end
			end

			spi_out = buffer;
			spi_io_vld = 1;

			if (verbose) begin
				if (bytecount == 1)
					$write("<SPI-START>");
				$write("<SPI:%02x:%02x>", spi_in, spi_out);
			end

		end
	endtask

	task ddr_rd_edge;
		begin
			buffer = {buffer, io3_delayed, io2_delayed, io1_delayed, io0_delayed};
			bitcount = bitcount + 4;
			if (bitcount == 8) begin
				bitcount = 0;
				bytecount = bytecount + 1;
				spi_action;
			end
		end
	endtask

	task ddr_wr_edge;
		begin
			io0_oe = 1;
			io1_oe = 1;
			io2_oe = 1;
			io3_oe = 1;

			io0_dout = buffer[4];
			io1_dout = buffer[5];
			io2_dout = buffer[6];
			io3_dout = buffer[7];

			buffer = {buffer, 4'h 0};
			bitcount = bitcount + 4;
			if (bitcount == 8) begin
				bitcount = 0;
				bytecount = bytecount + 1;
				spi_action;
			end
		end
	endtask

	always @(csb) begin
		if (csb) begin
			if (verbose) begin
				$display("");
				$fflush;
			end
			buffer = 0;
			bitcount = 0;
			bytecount = 0;
			mode = mode_spi;
			io0_oe = 0;
			io1_oe = 0;
			io2_oe = 0;
			io3_oe = 0;
		end else
		if (xip_cmd) begin
			buffer = xip_cmd;
			bitcount = 0;
			bytecount = 1;
			spi_action;
		end
	end

	always @(csb, clk) begin
		spi_io_vld = 0;
		if (!csb && !clk) begin
			if (dummycount > 0) begin
				io0_oe = 0;
				io1_oe = 0;
				io2_oe = 0;
				io3_oe = 0;
			end else
			case (mode)
				mode_spi: begin
					io0_oe = 0;
					io1_oe = 1;
					io2_oe = 0;
					io3_oe = 0;
					io1_dout = buffer[7];
				end
				mode_dspi_rd: begin
					io0_oe = 0;
					io1_oe = 0;
					io2_oe = 0;
					io3_oe = 0;
				end
				mode_dspi_wr: begin
					io0_oe = 1;
					io1_oe = 1;
					io2_oe = 0;
					io3_oe = 0;
					io0_dout = buffer[6];
					io1_dout = buffer[7];
				end
				mode_qspi_rd: begin
					io0_oe = 0;
					io1_oe = 0;
					io2_oe = 0;
					io3_oe = 0;
				end
				mode_qspi_wr: begin
					io0_oe = 1;
					io1_oe = 1;
					io2_oe = 1;
					io3_oe = 1;
					io0_dout = buffer[4];
					io1_dout = buffer[5];
					io2_dout = buffer[6];
					io3_dout = buffer[7];
				end
				mode_qspi_ddr_rd: begin
					ddr_rd_edge;
				end
				mode_qspi_ddr_wr: begin
					ddr_wr_edge;
				end
			endcase
			if (next_mode) begin
				case (next_mode)
					mode_qspi_ddr_rd: begin
						io0_oe = 0;
						io1_oe = 0;
						io2_oe = 0;
						io3_oe = 0;
					end
					mode_qspi_ddr_wr: begin
						io0_oe = 1;
						io1_oe = 1;
						io2_oe = 1;
						io3_oe = 1;
						io0_dout = buffer[4];
						io1_dout = buffer[5];
						io2_dout = buffer[6];
						io3_dout = buffer[7];
					end
				endcase
				mode = next_mode;
				next_mode = 0;
			end
		end
	end

	always @(posedge clk) begin
		if (!csb) begin
			if (dummycount > 0) begin
				dummycount = dummycount - 1;
			end else
			case (mode)
				mode_spi: begin
					buffer = {buffer, io0};
					bitcount = bitcount + 1;
					if (bitcount == 8) begin
						bitcount = 0;
						bytecount = bytecount + 1;
						spi_action;
					end
				end
				mode_dspi_rd, mode_dspi_wr: begin
					buffer = {buffer, io1, io0};
					bitcount = bitcount + 2;
					if (bitcount == 8) begin
						bitcount = 0;
						bytecount = bytecount + 1;
						spi_action;
					end
				end
				mode_qspi_rd, mode_qspi_wr: begin
					buffer = {buffer, io3, io2, io1, io0};
					bitcount = bitcount + 4;
					if (bitcount == 8) begin
						bitcount = 0;
						bytecount = bytecount + 1;
						spi_action;
					end
				end
				mode_qspi_ddr_rd: begin
					ddr_rd_edge;
				end
				mode_qspi_ddr_wr: begin
					ddr_wr_edge;
				end
			endcase
		end
	end
endmodule

femtoRV/cores/spi_flash/MappedSPIFlash.v
 `define SPI_FLASH_DUMMY_CLOCKS 0

module MappedSPIFlash( 
    input wire 	       clk,          // system clock
    input wire 	       rstrb,        // read strobe		
    input wire [19:0]  word_address, // address of the word to be read

    output wire [31:0] rdata,        // data read
    output wire        rbusy,        // asserted if busy receiving data			    

		             // SPI flash pins
    output wire        CLK,  // clock
    output reg         CS_N, // chip select negated (active low)		
    output wire        MOSI, // master out slave in (data to be sent to flash)
    input  wire        MISO  // master in slave out (data received from flash)
);

   reg [5:0]  snd_bitcount;
   reg [31:0] cmd_addr;
   reg [5:0]  rcv_bitcount;
   reg [31:0] rcv_data;
   wire       sending   = (snd_bitcount != 0);
   wire       receiving = (rcv_bitcount != 0);
   wire       busy = sending | receiving;
   assign     rbusy = !CS_N; 
   
   assign  MOSI  = cmd_addr[31];
   initial CS_N  = 1'b1;
   assign  CLK   = !CS_N && !clk; // CLK needs to be inverted (sample on posedge, shift of negedge) 
                                  // and needs to be disabled when not sending/receiving (&& !CS_N).

   // since least significant bytes are read first, we need to swizzle...
   assign rdata = {rcv_data[7:0],rcv_data[15:8],rcv_data[23:16],rcv_data[31:24]};
   
   always @(negedge clk) begin
      if(rstrb) begin
         CS_N <= 1'b0;
         cmd_addr <= {8'h03, 2'b00,word_address[19:0], 2'b00};
         snd_bitcount <= 6'd32;
      end else begin
         if(sending) begin
            if(snd_bitcount == 1) begin
               rcv_bitcount <= 6'd32;
            end
            snd_bitcount <= snd_bitcount - 6'd1;
            cmd_addr <= {cmd_addr[30:0],1'b1};
         end
         if(receiving) begin
            rcv_bitcount <= rcv_bitcount - 6'd1;
            rcv_data <= {rcv_data[30:0],MISO};
         end
         if(!busy) begin
            CS_N <= 1'b1;
         end
      end
   end
endmodule

tinytapeout/cores/spi_flash/MappedSPIFlash_TB.v
`timescale 1ns / 1ps
`define SIMULATION
module MappedSPIFlash_TB;
   reg  clk;
   reg  reset;
   reg  rstrb;
   reg  [19:0] word_address;

   wire [31:0] rdata;
   wire  rbusy;
   wire CLK;
   wire CS_N;
   wire MISO;
   wire MOSI;
   
   MappedSPIFlash uut (.clk(clk), .rstrb(rstrb) , .word_address(word_address) , .rdata(rdata) , .rbusy(rbusy) , .CLK(CLK) , .CS_N(CS_N), .MOSI(MOSI), .MISO(MISO)    );
 
  spiflash flash0(
    .csb(CS_N),
    .clk(CLK),
    .io0(MOSI), // MOSI
    .io1(MISO) // MISO
  );
    

   parameter PERIOD          = 20;
   parameter real DUTY_CYCLE = 0.5;
   parameter OFFSET          = 0;
   reg [20:0] i;
	 initial begin  // Initialize Inputs
      clk = 0; reset = 1; rstrb = 0; word_address = 20'h0000;
   end
   initial  begin  // Process for clk
     #OFFSET;
     forever
       begin
         clk = 1'b0;
         #(PERIOD-(PERIOD*DUTY_CYCLE)) clk = 1'b1;
         #(PERIOD*DUTY_CYCLE);
       end
   end
   initial begin // Reset the system, Start the image capture process
       repeat (3) @ (posedge clk);
       reset = 0;
       @ (posedge clk);
       reset = 1;
       for(i=0; i<32; i=i+1) begin
         repeat (1) @ (posedge clk);
         rstrb = 0;
         word_address = i;
         repeat (1) @ (posedge clk);
         rstrb = 1;
         repeat (1) @ (posedge clk);
         rstrb = 0;
         repeat (100*5) @ (posedge clk);



       end
   end	 
   initial begin: TEST_CASE
     $dumpfile("MappedSPIFlash_TB.vcd");
     $dumpvars(-1, uut);
     #((PERIOD*DUTY_CYCLE)*12000*5) $finish;
   end
endmodule

femtoRV/cores/spi_flash/MappedSPIFlash_TB.vcd
$date
	Mon May 12 07:17:13 2025
$end
$version
	Icarus Verilog
$end
$timescale
	1ps
$end
$scope module MappedSPIFlash_TB $end
$scope module uut $end
$var wire 1 ! CLK $end
$var wire 1 " MISO $end
$var wire 1 # busy $end
$var wire 1 $ clk $end
$var wire 1 % rstrb $end
$var wire 20 & word_address [19:0] $end
$var wire 1 ' sending $end
$var wire 1 ( receiving $end
$var wire 32 ) rdata [31:0] $end
$var wire 1 * rbusy $end
$var wire 1 + MOSI $end
$var reg 1 , CS_N $end
$var reg 32 - cmd_addr [31:0] $end
$var reg 6 . rcv_bitcount [5:0] $end
$var reg 32 / rcv_data [31:0] $end
$var reg 6 0 snd_bitcount [5:0] $end
$upscope $end
$upscope $end
$enddefinitions $end
#0
$dumpvars
bx 0
bx /
bx .
bx -
1,
x+
0*
bx )
x(
x'
b0 &
0%
0$
x#
x"
0!
$end
#1000
0"
#10000
1$
#20000
0$
#30000
1$
#40000
0$
#50000
1$
#60000
0$
#70000
1$
#80000
0$
#90000
1$
#100000
0$
#110000
1%
1$
#120000
1#
0+
1!
1'
b100000 0
b11000000000000000000000000 -
1*
0,
0$
#130000
0!
0%
1$
#140000
b110000000000000000000000001 -
b11111 0
1!
0$
#150000
0!
1$
#160000
b1100000000000000000000000011 -
b11110 0
1!
0$
#170000
0!
1$
#180000
b11000000000000000000000000111 -
b11101 0
1!
0$
#190000
0!
1$
#200000
b110000000000000000000000001111 -
b11100 0
1!
0$
#210000
0!
1$
#220000
b1100000000000000000000000011111 -
b11011 0
1!
0$
#230000
0!
1$
#240000
1+
b11000000000000000000000000111111 -
b11010 0
1!
0$
#250000
0!
1$
#260000
b10000000000000000000000001111111 -
b11001 0
1!
0$
#270000
0!
1$
#280000
0+
b11111111 -
b11000 0
1!
0$
#290000
0!
1$
#300000
b111111111 -
b10111 0
1!
0$
#310000
0!
1$
#320000
b1111111111 -
b10110 0
1!
0$
#330000
0!
1$
#340000
b11111111111 -
b10101 0
1!
0$
#350000
0!
1$
#360000
b111111111111 -
b10100 0
1!
0$
#370000
0!
1$
#380000
b1111111111111 -
b10011 0
1!
0$
#390000
0!
1$
#400000
b11111111111111 -
b10010 0
1!
0$
#410000
0!
1$
#411000
1"
#420000
b111111111111111 -
b10001 0
1!
0$
#430000
0!
1$
#440000
b1111111111111111 -
b10000 0
1!
0$
#450000
0!
1$
#451000
0"
#460000
b11111111111111111 -
b1111 0
1!
0$
#470000
0!
1$
#480000
b111111111111111111 -
b1110 0
1!
0$
#490000
0!
1$
#500000
b1111111111111111111 -
b1101 0
1!
0$
#510000
0!
1$
#520000
b11111111111111111111 -
b1100 0
1!
0$
#530000
0!
1$
#540000
b111111111111111111111 -
b1011 0
1!
0$
#550000
0!
1$
#560000
b1111111111111111111111 -
b1010 0
1!
0$
#570000
0!
1$
#580000
b11111111111111111111111 -
b1001 0
1!
0$
#590000
0!
1$
#600000
b111111111111111111111111 -
b1000 0
1!
0$
#610000
0!
1$
#620000
b1111111111111111111111111 -
b111 0
1!
0$
#630000
0!
1$
#640000
b11111111111111111111111111 -
b110 0
1!
0$
#650000
0!
1$
#660000
b111111111111111111111111111 -
b101 0
1!
0$
#670000
0!
1$
#680000
b1111111111111111111111111111 -
b100 0
1!
0$
#690000
0!
1$
#700000
b11111111111111111111111111111 -
b11 0
1!
0$
#710000
0!
1$
#720000
b111111111111111111111111111111 -
b10 0
1!
0$
#730000
0!
1$
#740000
b1111111111111111111111111111111 -
b1 0
1!
0$
#750000
0!
1$
#760000
1+
b11111111111111111111111111111111 -
0'
b0 0
1(
b100000 .
1!
0$
#770000
0!
1$
#780000
bx0xxxxxxxxxxxxxxxxxxxxxxxx )
bx0 /
b11111 .
1!
0$
#790000
0!
1$
#800000
bx00xxxxxxxxxxxxxxxxxxxxxxxx )
bx00 /
b11110 .
1!
0$
#810000
0!
1$
#811000
1"
#820000
bx001xxxxxxxxxxxxxxxxxxxxxxxx )
bx001 /
b11101 .
1!
0$
#830000
0!
1$
#840000
bx0011xxxxxxxxxxxxxxxxxxxxxxxx )
bx0011 /
b11100 .
1!
0$
#850000
0!
1$
#851000
0"
#860000
bx00110xxxxxxxxxxxxxxxxxxxxxxxx )
bx00110 /
b11011 .
1!
0$
#870000
0!
1$
#871000
1"
#880000
bx001101xxxxxxxxxxxxxxxxxxxxxxxx )
bx001101 /
b11010 .
1!
0$
#890000
0!
1$
#900000
bx0011011xxxxxxxxxxxxxxxxxxxxxxxx )
bx0011011 /
b11001 .
1!
0$
#910000
0!
1$
#920000
b110111xxxxxxxxxxxxxxxxxxxxxxxx )
bx00110111 /
b11000 .
1!
0$
#930000
0!
1$
#931000
0"
#940000
b1101110xxxxxxx0xxxxxxxxxxxxxxxx )
bx001101110 /
b10111 .
1!
0$
#950000
0!
1$
#960000
b11011100xxxxxx00xxxxxxxxxxxxxxxx )
bx0011011100 /
b10110 .
1!
0$
#970000
0!
1$
#980000
b10111000xxxxx001xxxxxxxxxxxxxxxx )
bx00110111000 /
b10101 .
1!
0$
#990000
0!
1$
#991000
1"
#1000000
b1110001xxxx0011xxxxxxxxxxxxxxxx )
bx001101110001 /
b10100 .
1!
0$
#1010000
0!
1$
#1011000
0"
#1020000
b11100010xxx00110xxxxxxxxxxxxxxxx )
bx0011011100010 /
b10011 .
1!
0$
#1030000
0!
1$
#1040000
b11000100xx001101xxxxxxxxxxxxxxxx )
bx00110111000100 /
b10010 .
1!
0$
#1050000
0!
1$
#1060000
b10001000x0011011xxxxxxxxxxxxxxxx )
bx001101110001000 /
b10001 .
1!
0$
#1070000
0!
1$
#1071000
1"
#1080000
b1000100110111xxxxxxxxxxxxxxxx )
bx0011011100010001 /
b10000 .
1!
0$
#1090000
0!
1$
#1091000
0"
#1100000
b10001001101110xxxxxxx0xxxxxxxx )
bx00110111000100010 /
b1111 .
1!
0$
#1110000
0!
1$
#1120000
b100010011011100xxxxxx00xxxxxxxx )
bx001101110001000100 /
b1110 .
1!
0$
#1130000
0!
1$
#1140000
b1000100010111000xxxxx001xxxxxxxx )
bx0011011100010001000 /
b1101 .
1!
0$
#1150000
0!
1$
#1160000
b1000001110001xxxx0011xxxxxxxx )
bx00110111000100010000 /
b1100 .
1!
0$
#1170000
0!
1$
#1180000
b10000011100010xxx00110xxxxxxxx )
bx001101110001000100000 /
b1011 .
1!
0$
#1190000
0!
1$
#1200000
b100000011000100xx001101xxxxxxxx )
bx0011011100010001000000 /
b1010 .
1!
0$
#1210000
0!
1$
#1220000
b1000000010001000x0011011xxxxxxxx )
bx00110111000100010000000 /
b1001 .
1!
0$
#1230000
0!
1$
#1240000
b1000100110111xxxxxxxx )
bx001101110001000100000000 /
b1000 .
1!
0$
#1250000
0!
1$
#1260000
b10001001101110xxxxxxx0 )
bx0011011100010001000000000 /
b111 .
1!
0$
#1270000
0!
1$
#1280000
b100010011011100xxxxxx00 )
bx00110111000100010000000000 /
b110 .
1!
0$
#1290000
0!
1$
#1300000
b1000100010111000xxxxx001 )
bx001101110001000100000000000 /
b101 .
1!
0$
#1310000
0!
1$
#1320000
b1000001110001xxxx0011 )
bx0011011100010001000000000000 /
b100 .
1!
0$
#1330000
0!
1$
#1340000
b10000011100010xxx00110 )
bx00110111000100010000000000000 /
b11 .
1!
0$
#1350000
0!
1$
#1360000
b100000011000100xx001101 )
bx001101110001000100000000000000 /
b10 .
1!
0$
#1370000
0!
1$
#1380000
b1000000010001000x0011011 )
bx0011011100010001000000000000000 /
b1 .
1!
0$
#1390000
0!
1$
#1400000
b1000100110111 )
0#
b110111000100010000000000000000 /
0(
b0 .
1!
0$
#1410000
0!
1$
#1420000
0*
1,
0!
0$
